{
  "db_name": "PostgreSQL",
  "query": "\n                SELECT *\n                FROM users\n                WHERE\n                    id = $1\n            ",
  "describe": {
    "columns": [
      {
        "ordinal": 0,
        "name": "id",
        "type_info": "Int8"
      },
      {
        "ordinal": 1,
        "name": "username",
        "type_info": "Text"
      },
      {
        "ordinal": 2,
        "name": "email",
        "type_info": "Text"
      },
      {
        "ordinal": 3,
        "name": "password",
        "type_info": "Varchar"
      },
      {
        "ordinal": 4,
        "name": "created_at",
        "type_info": "Timestamp"
      }
    ],
    "parameters": {
      "Left": [
        "Int8"
      ]
    },
    "nullable": [
      false,
      false,
      false,
      false,
      false
    ]
  },
  "hash": "29b216094d3d32076f8d62adac7bc38351082c9878d6ba6c408671b67850dc70"
}
